[{"n":"天津","s":[{"n":"津价房地(2008)136号","s":[{"n":"0|100|500|1000|5000|10000","s":[{"n":"编制项目投资估算","s":[{"n":"建安工程费用","s":[{"n":"0.8|0.7|0.6|0.5|0.3|0.15","s":[{"n":"hiddenhidden","s":[{"n":"hiddenhidden","s":[{"n":"hiddenhidden","s":[{"n":"hiddenhidden","s":[{"n":"hiddenhidden","s":null}]}]}]}]}]}]}]},{"n":"编制设计概算","s":[{"n":"建安工程费用","s":[{"n":"1.7|1.5|1.2|0.85|0.7|0.4","s":[{"n":"hiddenhidden","s":[{"n":"hiddenhidden","s":[{"n":"hiddenhidden","s":[{"n":"hiddenhidden","s":[{"n":"hiddenhidden","s":null}]}]}]}]}]}]}]},{"n":"工程造价编制-编制工程量清单","s":[{"n":"工程总造价","s":[{"n":"3.4|3.2|3.0|2.4|2.0|1.6","s":[{"n":"hiddenhidden","s":[{"n":"hiddenhidden","s":[{"n":"hiddenhidden","s":[{"n":"hiddenhidden","s":[{"n":"hiddenhidden","s":null}]}]}]}]}]}]}]},{"n":"工程造价编制-编制标底(含清单)","s":[{"n":"工程总造价","s":[{"n":"3.6|3.4|3.1|2.6|2.0|1.7","s":[{"n":"hiddenhidden","s":[{"n":"hiddenhidden","s":[{"n":"hiddenhidden","s":[{"n":"hiddenhidden","s":[{"n":"hiddenhidden","s":null}]}]}]}]}]}]}]},{"n":"工程造价编制-编制施工图预算","s":[{"n":"工程总造价","s":[{"n":"3.6|3.4|3.1|2.6|2.0|1.7","s":[{"n":"hiddenhidden","s":[{"n":"hiddenhidden","s":[{"n":"hiddenhidden","s":[{"n":"hiddenhidden","s":[{"n":"hiddenhidden","s":null}]}]}]}]}]}]}]},{"n":"工程造价编制-编制竣工结算","s":[{"n":"工程总造价","s":[{"n":"3.6|3.4|3.1|2.6|2.0|1.7","s":[{"n":"hiddenhidden","s":[{"n":"hiddenhidden","s":[{"n":"hiddenhidden","s":[{"n":"hiddenhidden","s":[{"n":"hiddenhidden","s":null}]}]}]}]}]}]}]},{"n":"施工阶段全过程造价控制","s":[{"n":"工程总造价","s":[{"n":"10|9.0|8.0|7.5|7.0|6.0","s":[{"n":"hiddenhidden","s":[{"n":"hiddenhidden","s":[{"n":"hiddenhidden","s":[{"n":"hiddenhidden","s":[{"n":"hiddenhidden","s":null}]}]}]}]}]}]}]},{"n":"工程造价审核-基本收费（±5%以内）-审核概算","s":[{"n":"送审工程总造价","s":[{"n":"3.0|2.5|2.0|1.5|1.2|1.0","s":[{"n":"审定额：","s":[{"n":"核增核减超过比：","s":[{"n":"0","s":[{"n":"收费费率：","s":[{"n":"5","s":null}]}]}]}]}]}]}]},{"n":"工程造价审核-基本收费（±5%以内）-审核预算、标底","s":[{"n":"送审工程总造价","s":[{"n":"3.5|3.1|2.2|1.9|1.2|0.9","s":[{"n":"审定额：","s":[{"n":"核增核减超过比：","s":[{"n":"0","s":[{"n":"收费费率：","s":[{"n":"5","s":null}]}]}]}]}]}]}]},{"n":"工程造价审核-基本收费（±5%以内）-审核竣工结算","s":[{"n":"送审工程总造价","s":[{"n":"3.5|3.1|2.2|1.9|1.2|0.9","s":[{"n":"审定额：","s":[{"n":"核增核减超过比：","s":[{"n":"0","s":[{"n":"收费费率：","s":[{"n":"5","s":null}]}]}]}]}]}]}]},{"n":"工程造价争议鉴定","s":[{"n":"鉴定标的","s":[{"n":"40|40|20|20|20|20","s":[{"n":"hiddenhidden","s":[{"n":"hiddenhidden","s":[{"n":"hiddenhidden","s":[{"n":"hiddenhidden","s":[{"n":"hiddenhidden","s":null}]}]}]}]}]}]}]}]}]}]}]