[{"n":"西藏","s":[{"n":"藏价费〔2002〕69号","s":[{"n":"避雷针","s":[{"n":"支","s":[{"n":"150","s":null}]}]},{"n":"避雷带(网)引下线","s":[{"n":"测点","s":[{"n":"150","s":null}]}]},{"n":"天线及多属基座接地","s":[{"n":"测点","s":[{"n":"150","s":null}]}]},{"n":"玻璃幕墙支架","s":[{"n":"测点","s":[{"n":"600","s":null}]}]},{"n":"金属架广告牌接地","s":[{"n":"测点","s":[{"n":"150","s":null}]}]},{"n":"10层及以上防侧击雷","s":[{"n":"测点","s":[{"n":"200","s":null}]}]},{"n":"水塔防雷装置及接地","s":[{"n":"测点","s":[{"n":"200","s":null}]}]},{"n":"烟囱防雷装置及接地","s":[{"n":"测点","s":[{"n":"200","s":null}]}]},{"n":"电梯防雷装置及接地","s":[{"n":"测点","s":[{"n":"200","s":null}]}]},{"n":"古建筑防雷引下线","s":[{"n":"根","s":[{"n":"180","s":null}]}]},{"n":"静电检测加油机","s":[{"n":"台","s":[{"n":"40","s":null}]}]},{"n":"静电检测充气枪","s":[{"n":"支","s":[{"n":"30","s":null}]}]},{"n":"卸油(气)台检测","s":[{"n":"台","s":[{"n":"60","s":null}]}]},{"n":"附件(呼吸阀.金属棚.法栏)","s":[{"n":"项","s":[{"n":"50","s":null}]}]},{"n":"电源 高压接地","s":[{"n":"测点","s":[{"n":"80","s":null}]}]},{"n":"系统 低压接地","s":[{"n":"测点","s":[{"n":"60","s":null}]}]},{"n":"配电柜接地","s":[{"n":"测点","s":[{"n":"50","s":null}]}]},{"n":"计算机 防静电及布局接地","s":[{"n":"间(机房)","s":[{"n":"300","s":null}]}]},{"n":"零地电压","s":[{"n":"测点","s":[{"n":"40","s":null}]}]},{"n":"电磁环境测试","s":[{"n":"间(机房)","s":[{"n":"250","s":null}]}]},{"n":"特殊测试","s":[{"n":"测点","s":[{"n":"80","s":null}]}]},{"n":"总电源避雷器","s":[{"n":"套","s":[{"n":"150","s":null}]}]},{"n":"避雷器 分电源避雷器","s":[{"n":"只","s":[{"n":"40","s":null}]}]},{"n":"测试 避雷器元件","s":[{"n":"只","s":[{"n":"60","s":null}]}]}]}]}]